transit_service_analyst/__init__.py
transit_service_analyst/gtfs_schema.py
transit_service_analyst/gtfs_service.py
transit_service_analyst/load_gtfs.py
transit_service_analyst-0.1.4.dist-info/LICENSE
transit_service_analyst-0.1.4.dist-info/METADATA
transit_service_analyst-0.1.4.dist-info/WHEEL
transit_service_analyst-0.1.4.dist-info/top_level.txt
transit_service_analyst-0.1.4.dist-info/RECORD
