Metadata-Version: 2.1
Name: transit-service-analyst
Version: 0.1.4
Summary: Tools to support transit service analysis
Author: psrc staff
Author-email: scoe@psrc.org
Requires-Python: >=3.7
License-File: LICENSE
